npgp/__init__.py
npgp/cli.py
npgp/templates/__init__.py
npgp/templates/basic.py
npgp/templates/class.py
npgp/templates/config.py
npgp-1.0.0.dist-info/METADATA
npgp-1.0.0.dist-info/WHEEL
npgp-1.0.0.dist-info/entry_points.txt
npgp-1.0.0.dist-info/top_level.txt
npgp-1.0.0.dist-info/RECORD
