Metadata-Version: 2.4
Name: npgp
Version: 1.0.0
Summary: A CLI to create new Pygame project from a template
Author: clxakz
Author-email: zolotarjovdavid15@gmail.com
Classifier: Programming Language :: Python :: 3
Classifier: License :: OSI Approved :: MIT License
Requires-Python: >=3.7
Dynamic: author
Dynamic: author-email
Dynamic: classifier
Dynamic: requires-python
Dynamic: summary
